{"blue_utility": "28.779099385265795", "red_utility": "16.753198509188362", "blue_select1": "Viego", "blue_select2": "Zeri", "blue_select3": "Gwen", "blue_select4": "Nami", "blue_select5": "Twisted Fate", "red_select1": "Gnar", "red_select2": "Lulu", "red_select3": "Diana", "red_select4": "Ryze", "red_select5": "Varus", "blue_ban1": "Xin Zhao", "blue_ban2": "Aphelios", "blue_ban3": "Ezreal", "blue_ban4": "LeBlanc", "blue_ban5": "Jinx", "red_ban1": "Lucian", "red_ban2": "Sivir", "red_ban3": "Karthus", "red_ban4": "Samira", "red_ban5": "Kalista"}