{"blue_utility": "29.97726432606039", "red_utility": "16.84683742248141", "blue_select1": "Nautilus", "blue_select2": "LeBlanc", "blue_select3": "Lee Sin", "blue_select4": "Gnar", "blue_select5": "Ezreal", "red_select1": "Xin Zhao", "red_select2": "Jhin", "red_select3": "Graves", "red_select4": "Renekton", "red_select5": "Renata Glasc", "blue_ban1": "Jarvan IV", "blue_ban2": "Ornn", "blue_ban3": "Aphelios", "blue_ban4": "Rakan", "blue_ban5": "Azir", "red_ban1": "Kalista", "red_ban2": "Jinx", "red_ban3": "Sivir", "red_ban4": "Lucian", "red_ban5": "Karthus"}