{"blue_utility": "26.87236987838462", "red_utility": "15.619315143676104", "blue_select1": "Nautilus", "blue_select2": "Jarvan IV", "blue_select3": "LeBlanc", "blue_select4": "Gnar", "blue_select5": "Ezreal", "red_select1": "Lulu", "red_select2": "Draven", "red_select3": "Volibear", "red_select4": "Gangplank", "red_select5": "Corki", "blue_ban1": "Jinx", "blue_ban2": "Xin Zhao", "blue_ban3": "Wukong", "blue_ban4": "Yuumi", "blue_ban5": "Gwen", "red_ban1": "Zeri", "red_ban2": "Kalista", "red_ban3": "Aphelios", "red_ban4": "Twitch", "red_ban5": "Samira"}