{"blue_utility": "31.533278817850263", "red_utility": "17.259428458484965", "blue_select1": "Vex", "blue_select2": "Viego", "blue_select3": "Leona", "blue_select4": "Graves", "blue_select5": "Zeri", "red_select1": "Lee Sin", "red_select2": "Lulu", "red_select3": "Jayce", "red_select4": "Taliyah", "red_select5": "Jhin", "blue_ban1": "Jarvan IV", "blue_ban2": "Ornn", "blue_ban3": "Aphelios", "blue_ban4": "Rakan", "blue_ban5": "Azir", "red_ban1": "Lucian", "red_ban2": "Draven", "red_ban3": "Jinx", "red_ban4": "Karthus", "red_ban5": "Twitch"}