{"blue_utility": "30.808867793940653", "red_utility": "21.367148939956525", "blue_select1": "Viego", "blue_select2": "Gwen", "blue_select3": "Lucian", "blue_select4": "LeBlanc", "blue_select5": "Nami", "red_select1": "Ornn", "red_select2": "Jhin", "red_select3": "Wukong", "red_select4": "Lulu", "red_select5": "Swain", "blue_ban1": "Nautilus", "blue_ban2": "Jinx", "blue_ban3": "Lee Sin", "blue_ban4": "Taliyah", "blue_ban5": "Aatrox", "red_ban1": "Zeri", "red_ban2": "Aphelios", "red_ban3": "Draven", "red_ban4": "Twitch", "red_ban5": "Sivir"}